Metadata-Version: 2.1
Name: google-play-scraper-py-trkjoy
Version: 1.2.72
Summary: Google-Play-Scraper provides APIs to easily crawl the Google Play Store for Python without any external dependencies!
Home-page: https://github.com/trkjoy/google-play-scraper-py-trkjoy
License: MIT
Author: trkjoy
Author-email: trkjoy.planb@gmail.com
Requires-Python: >=3.7,<4.0
Classifier: Development Status :: 5 - Production/Stable
Classifier: License :: OSI Approved :: MIT License
Classifier: Operating System :: MacOS
Classifier: Operating System :: Microsoft
Classifier: Programming Language :: Python
Classifier: Programming Language :: Python :: 3
Classifier: Programming Language :: Python :: 3.7
Classifier: Programming Language :: Python :: 3.8
Classifier: Programming Language :: Python :: 3.9
Classifier: Programming Language :: Python :: 3.10
Classifier: Programming Language :: Python :: 3.11
Classifier: Programming Language :: Python :: 3.12
Classifier: Programming Language :: Python :: 3.13
Classifier: Programming Language :: Python :: 3.6
Classifier: Topic :: Software Development :: Libraries :: Python Modules
Classifier: Topic :: Utilities
Classifier: Typing :: Typed
Project-URL: Repository, https://github.com/trkjoy/google-play-scraper-py-trkjoy
